ldapKIT/__init__.py
ldapKIT/config.py
ldapKIT/ldapKIT.py
ldapKIT/particleldapchangemail.py
ldapKIT/particleldapgroup.py
ldapKIT/particleldapresetpassword.py
ldapKIT/particleldapuseradd.py
ldapKIT/particleldapuserdel.py
ldapkit-1.4.10.dist-info/entry_points.txt
ldapkit-1.4.10.dist-info/WHEEL
ldapkit-1.4.10.dist-info/METADATA
ldapkit-1.4.10.dist-info/RECORD
