Metadata-Version: 2.1
Name: ldapKIT
Version: 1.4.10
Summary: Collection of useful scripts for ldap based user management.
Home-page: https://github.com/particleKIT/ldapKIT.git
Author: Martin Gabelmann, Robin Roth
Author-email: martin@gabelmann.biz
Classifier: License :: OSI Approved :: GNU General Public License v3 or later (GPLv3+)
Requires-Dist: python_gitlab
Requires-Dist: xkcdpass
Requires-Dist: gnupg
Requires-Dist: python_ldap
Requires-Dist: PyYAML
